{"model_type": "CatBoost", "n_features": 22, "feature_importances": [4.013943671010378, 5.168101980514044, 1.6394296580193437, 2.0260911393733307, 1.0316143166606888, 6.97118929929577, 6.08588029533583, 15.395411573784928, 1.1666580917925211, 0.19091489879996998, 1.4643636538977838, 6.042628519890557, 24.90080727671587, 8.768577464264123, 7.115768220685052, 1.3217332852221029, 1.7402983892815387, 1.5321292918468843, 0.8401566311268028, 0.20473190673329444, 1.0097139663088992, 1.3698564694402688], "classes": ["-1", "1"], "params": {"nan_mode": "Min", "eval_metric": "Logloss", "iterations": 500, "sampling_frequency": "PerTree", "leaf_estimation_method": "Newton", "random_score_type": "NormalWithModelSizeDecrease", "grow_policy": "SymmetricTree", "penalties_coefficient": 1, "boosting_type": "Plain", "model_shrink_mode": "Constant", "feature_border_type": "GreedyLogSum", "bayesian_matrix_reg": 0.10000000149011612, "eval_fraction": 0, "force_unit_auto_pair_weights": false, "l2_leaf_reg": 3, "random_strength": 1, "rsm": 1, "boost_from_average": false, "model_size_reg": 0.5, "pool_metainfo_options": {"tags": {}}, "subsample": 0.800000011920929, "use_best_model": false, "class_names": ["-1", "1"], "random_seed": 0, "depth": 6, "posterior_sampling": false, "border_count": 254, "classes_count": 0, "auto_class_weights": "None", "sparse_features_conflict_fraction": 0, "leaf_estimation_backtracking": "AnyImprovement", "best_model_min_trees": 1, "model_shrink_rate": 0, "min_data_in_leaf": 1, "loss_function": "Logloss", "learning_rate": 0.10000000149011612, "score_function": "Cosine", "task_type": "CPU", "leaf_estimation_iterations": 10, "bootstrap_type": "MVS", "max_leaves": 64}}